MANIFEST.in
README.md
setup.py
RESOURCES/.suffix
RESOURCES/dummy
gplean/__init__.py
gplean/engine.py
gplean/gpcfg.py
gplean/obj.py
gplean/query.py
gplean/user.py
gplean.egg-info/PKG-INFO
gplean.egg-info/SOURCES.txt
gplean.egg-info/dependency_links.txt
gplean.egg-info/entry_points.txt
gplean.egg-info/top_level.txt
gplean/bin/__init__.py
gplean/bin/cfg_enable_regis.py
gplean/bin/obj_creat_cls.py
gplean/bin/obj_del_one_row.py
gplean/bin/obj_insert_one_row.py
gplean/bin/obj_update_one_row.py
gplean/bin/query_count.py
gplean/bin/query_query.py
gplean/bin/user_get_all_users.py
gplean/bin/user_login.py
gplean/bin/user_me.py
gplean/bin/user_modify_password_via_xlc_sess.py
gplean/bin/user_regis.py
gplean/bin/user_update.py