Metadata-Version: 1.1
Name: gplean
Version: 0.0.10
Summary: handle,.in progressing..,APIs
Home-page: https://github.com/3620373489/gplean
Author: 3620373489
Author-email: UNKNOWN
License: MIT
Platform: UNKNOWN
Classifier: Environment :: Console
Classifier: Environment :: Web Environment
Classifier: Intended Audience :: End Users/Desktop
Classifier: Intended Audience :: Developers
Classifier: Intended Audience :: System Administrators
Classifier: Programming Language :: Python
